{
    "items": [
        {
            "cell_id": 1,
            "done": false,
            "pick": false,
            "product": ""
        },
        {
            "cell_id": 2,
            "done": false,
            "pick": false,
            "product": ""
        },
        {
            "cell_id": 3,
            "done": false,
            "pick": false,
            "product": ""
        },
        {
            "cell_id": 4,
            "done": false,
            "pick": false,
            "product": ""
        },
        {
            "cell_id": 5,
            "done": false,
            "pick": false,
            "product": ""
        },
        {
            "cell_id": 6,
            "done": false,
            "pick": false,
            "product": ""
        },
        {
            "cell_id": 7,
            "done": false,
            "pick": false,
            "product": ""
        },
        {
            "cell_id": 8,
            "done": true,
            "pick": false,
            "product": ""
        },
        {
            "cell_id": 9,
            "done": false,
            "pick": true,
            "product": "Bánh quy"
        }
    ]
}